{
	"easycom": {
		"^u-(.*)": "uview-ui/components/u-$1/u-$1.vue"
	},
	"pages": [ //pages数组中第一项表示应用启动页，参考：https://uniapp.dcloud.io/collocation/pages
		{
			"path": "pages/home/index/index",
			"style": {
				"navigationBarTitleText": "天目红盟"
			}
		},
		{
			"path": "pages/home/point-guide/index",
			"style": {
				"navigationBarTitleText": "地标导览"
			}
		},
		{
			"path": "pages/home/stroke-order/index",
			"style": {
				"navigationBarTitleText": "创建行程单"
			}
		},
		{
			"path": "pages/home/stroke-order/VenueMap",
			"style": {
				"navigationBarTitleText": "选择集合点"
			}
		},
		{
			"path": "pages/home/stroke-order/createSuccess",
			"style": {
				"navigationBarTitleText": "创建成功"
			}
		},
		{
			"path": "pages/home/stroke-order/detail",
			"style": {
				"navigationBarTitleText": "行程单"
			}
		},
		{
			"path": "pages/home/stroke-order/CustomPath",
			"style": {
				"navigationBarTitleText": "自定义路线"
			}
		},
		{
			"path": "pages/home/stroke-order/GetRedPoints",
			"style": {
				"navigationBarTitleText": "添加红色地标"
			}
		},
		{
			"path": "pages/home/evaluate-detail/index",
			"style": {
				"navigationBarTitleText": "评价详情"
			}
		},
		{
			"path": "pages/public/Login",
			"style": {
				"navigationBarTitleText": "授权"
			}
		},
		{
			"path": "pages/public/Bind",
			"style": {
				"navigationBarTitleText": "注册登录"
			}
		},
		{
			"path": "pages/party/index/index",
			"style": {
				"navigationBarTitleText": "党建联盟"
			}
		},
		{
			"path": "pages/league-interact/index/index",
			"style": {
				"navigationBarTitleText": "联盟互动"
			}
		},
		{
			"path": "pages/mine/index/index",
			"style": {
				"navigationBarTitleText": "我的"
			}
		},
		{
			"path": "pages/webView",
			"style": {
				"navigationBarTitleText": ""
			}
		}
	],
	"globalStyle": {
		"navigationBarTextStyle": "black",
		"navigationBarTitleText": "uni-app",
		"navigationBarBackgroundColor": "#F8F8F8",
		"backgroundColor": "#F8F8F8",
		"app-plus": {"titleNView": false}
	},
	"tabBar": {
		"color": "#666666",
		"selectedColor": "#f54400",
		"fontSize": "12px",
		"iconWidth": "20px",
		"borderStyle": "#00000010",
		"backgroundColor": "#ffffff",
		"list": [
			{
				"pagePath": "pages/home/index/index",
				"iconPath": "static/tabbar/original.png",
				"selectedIconPath": "static/tabbar/original_l.png",
				"text": "初心之旅"
			},
			{
				"pagePath": "pages/party/index/index",
				"iconPath": "static/tabbar/party.png",
				"selectedIconPath": "static/tabbar/party_l.png",
				"text": "党建联盟"
			},
			{
				"pagePath": "pages/league-interact/index/index",
				"iconPath": "static/tabbar/interact.png",
				"selectedIconPath": "static/tabbar/interact_l.png",
				"text": "联盟互动"
			},
			{
				"pagePath": "pages/mine/index/index",
				"iconPath": "static/tabbar/mine.png",
				"selectedIconPath": "static/tabbar/mine_l.png",
				"text": "我的"
			}
		]
	}
}